{
	"status": "1",
    "data": {
	"skip_count": 0,
	"days": [
		{
			"date": "2022-05-31",
			"providers": [
				{
					"total": 23,
					"provider_id": 119,
					"items": [
						{
							"jw_entity_id": "tss311662",
							"id": 311662,
							"title": "Season 7",
							"full_path": "/in/tv-show/fear-the-walking-dead/season-7",
							"poster": "/poster/268875310/{profile}",
							"backdrops": [
								{
									"backdrop_url": "/backdrop/269914818/{profile}",
									"backdrop_blur_hash": "L9840nAHq_t5}nNvVuX7NH#-OXW;"
								},
								{
									"backdrop_url": "/backdrop/251388321/{profile}",
									"backdrop_blur_hash": "LKQ6]A9K+b+wESIX%c?V~i,:y9Sz"
								},
								{
									"backdrop_url": "/backdrop/251388322/{profile}",
									"backdrop_blur_hash": "LKPWp80Q]~^0%0#+x?xr%vi{y9kS"
								},
								{
									"backdrop_url": "/backdrop/208379163/{profile}",
									"backdrop_blur_hash": "L34LaxWC0Jxu-:WBIot7V]j[jZWB"
								},
								{
									"backdrop_url": "/backdrop/243989549/{profile}",
									"backdrop_blur_hash": "L}IFe;of~XfjM{afWBaysoWVkCay"
								}
							],
							"tmdb_popularity": 397.562,
							"object_type": "show_season",
							"original_title": "7ος κύκλος",
							"offers": [
								{
									"jw_entity_id": "tss311662",
									"type": "aggregated",
									"monetization_type": "flatrate",
									"provider_id": 119,
									"package_short_name": "prv",
									"currency": "INR",
									"urls": {
										"standard_web": "https://app.primevideo.com/detail?gti=amzn1.dv.gti.d40a6bb0-c957-4ac0-884c-bb4cd34c21bc",
										"deeplink_web": "https://app.primevideo.com/watch?gti=amzn1.dv.gti.d40a6bb0-c957-4ac0-884c-bb4cd34c21bc",
										"deeplink_rokuos": "launch/13?contentID=B09JFMLPGK&MediaType=episode"
									},
									"presentation_type": "sd",
									"element_count": 15,
									"new_element_count": 1,
									"country": "IN"
								}
							],
							"scoring": [
								{
									"provider_type": "tmdb:score",
									"value": 7.7
								},
								{
									"provider_type": "imdb:score",
									"value": 6.8
								},
								{
									"provider_type": "tmdb:popularity",
									"value": 397.562
								},
								{
									"provider_type": "imdb:votes",
									"value": 127089
								},
								{
									"provider_type": "imdb:multiplied",
									"value": 864205.2
								},
								{
									"provider_type": "imdb:popularity",
									"value": 101
								}
							],
							"show_id": 36000,
							"show_title": "Fear the Walking Dead",
							"season_number": 7
						},
						{
							"jw_entity_id": "tss235032",
							"id": 235032,
							"title": "Season 1",
							"full_path": "/in/tv-show/bang-bang-baby/season-1",
							"poster": "/poster/278627087/{profile}",
							"backdrops": [
								{
									"backdrop_url": "/backdrop/272395426/{profile}",
									"backdrop_blur_hash": "LVExi8*^RkK5AS#?r?S$VCX:bZrX"
								}
							],
							"tmdb_popularity": 9.771,
							"object_type": "show_season",
							"original_title": "Sezonul 1",
							"offers": [
								{
									"jw_entity_id": "tss235032",
									"type": "aggregated",
									"monetization_type": "flatrate",
									"provider_id": 119,
									"package_short_name": "prv",
									"currency": "INR",
									"urls": {
										"standard_web": "https://app.primevideo.com/detail?gti=amzn1.dv.gti.1d31b3fd-617d-497f-9de5-21cc0a4cd18e",
										"deeplink_web": "https://app.primevideo.com/watch?gti=amzn1.dv.gti.1d31b3fd-617d-497f-9de5-21cc0a4cd18e",
										"deeplink_rokuos": "launch/13?contentID=B09XK67MVY&MediaType=episode"
									},
									"presentation_type": "sd",
									"element_count": 10,
									"new_element_count": 5,
									"country": "IN"
								}
							],
							"scoring": [
								{
									"provider_type": "tmdb:popularity",
									"value": 9.771
								},
								{
									"provider_type": "imdb:votes",
									"value": 152
								},
								{
									"provider_type": "imdb:multiplied",
									"value": 957.6
								},
								{
									"provider_type": "tmdb:score",
									"value": 8.3
								},
								{
									"provider_type": "imdb:score",
									"value": 6.3
								}
							],
							"show_id": 224849,
							"season_number": 1
						},
						{
							"jw_entity_id": "tm86968",
							"id": 86968,
							"title": "Aitraaz",
							"full_path": "/in/movie/aitraaz",
							"poster": "/poster/191751617/{profile}",
							"tmdb_popularity": 7.025,
							"object_type": "movie",
							"original_title": "ऐतराज़",
							"offers": [
								{
									"jw_entity_id": "tm86968",
									"monetization_type": "flatrate",
									"provider_id": 119,
									"package_short_name": "prv",
									"currency": "INR",
									"urls": {
										"standard_web": "https://app.primevideo.com/detail?gti=amzn1.dv.gti.c27a6554-406d-42bc-b1e2-9cc1ddc8a82b",
										"deeplink_web": "https://app.primevideo.com/watch?gti=amzn1.dv.gti.c27a6554-406d-42bc-b1e2-9cc1ddc8a82b",
										"deeplink_rokuos": "launch/13?contentID=B0B1TZYK93&MediaType=movie"
									},
									"presentation_type": "sd",
									"country": "IN"
								}
							],
							"scoring": [
								{
									"provider_type": "tmdb:id",
									"value": 22315
								},
								{
									"provider_type": "imdb:multiplied",
									"value": 67405.8
								},
								{
									"provider_type": "tmdb:score",
									"value": 5.7
								},
								{
									"provider_type": "imdb:score",
									"value": 6.6
								},
								{
									"provider_type": "tmdb:popularity",
									"value": 7.025
								},
								{
									"provider_type": "imdb:votes",
									"value": 10213
								}
							]
						},
						{
							"jw_entity_id": "tm186785",
							"id": 186785,
							"title": "Khal Nayak",
							"full_path": "/in/movie/khal-nayak",
							"poster": "/poster/207353298/{profile}",
							"backdrops": [
								{
									"backdrop_url": "/backdrop/58690148/{profile}",
									"backdrop_blur_hash": "LGB.1W?bxvNeIoM|R*od1a+]RjEf"
								},
								{
									"backdrop_url": "/backdrop/58690149/{profile}",
									"backdrop_blur_hash": "LMKcFN}qf#ivDkSgW-^kKdozsDIo"
								},
								{
									"backdrop_url": "/backdrop/415691/{profile}",
									"backdrop_blur_hash": "L6E_aXI.V@0dTL9tX9xb57$*WAof"
								}
							],
							"tmdb_popularity": 3.548,
							"object_type": "movie",
							"original_title": "Khal Nayak",
							"offers": [
								{
									"jw_entity_id": "tm186785",
									"monetization_type": "flatrate",
									"provider_id": 119,
									"package_short_name": "prv",
									"currency": "INR",
									"urls": {
										"standard_web": "https://app.primevideo.com/detail?gti=amzn1.dv.gti.ffa69cb4-bb80-49aa-98ef-255a9911b150",
										"deeplink_web": "https://app.primevideo.com/watch?gti=amzn1.dv.gti.ffa69cb4-bb80-49aa-98ef-255a9911b150",
										"deeplink_rokuos": "launch/13?contentID=B09V1LTM6F&MediaType=movie"
									},
									"presentation_type": "sd",
									"country": "IN"
								}
							],
							"scoring": [
								{
									"provider_type": "imdb:votes",
									"value": 3310
								},
								{
									"provider_type": "tmdb:id",
									"value": 32295
								},
								{
									"provider_type": "imdb:multiplied",
									"value": 23501
								},
								{
									"provider_type": "tmdb:score",
									"value": 7
								},
								{
									"provider_type": "imdb:score",
									"value": 7.1
								},
								{
									"provider_type": "tmdb:popularity",
									"value": 3.548
								}
							]
						},
						{
							"jw_entity_id": "tm6781",
							"id": 6781,
							"title": "Saudagar",
							"full_path": "/in/movie/saudagar",
							"poster": "/poster/138451950/{profile}",
							"backdrops": [
								{
									"backdrop_url": "/backdrop/156765212/{profile}",
									"backdrop_blur_hash": "LHDlAi=[-4?H0.IpRjS7Ost6NvtQ"
								}
							],
							"tmdb_popularity": 2.75,
							"object_type": "movie",
							"original_title": "सौदागर",
							"offers": [
								{
									"jw_entity_id": "tm6781",
									"monetization_type": "flatrate",
									"provider_id": 119,
									"package_short_name": "prv",
									"currency": "INR",
									"urls": {
										"standard_web": "https://app.primevideo.com/detail?gti=amzn1.dv.gti.9962c6e1-92e6-483e-9f49-8adf903c8bd8",
										"deeplink_web": "https://app.primevideo.com/watch?gti=amzn1.dv.gti.9962c6e1-92e6-483e-9f49-8adf903c8bd8",
										"deeplink_rokuos": "launch/13?contentID=B09WZMSDGB&MediaType=movie"
									},
									"presentation_type": "sd",
									"country": "IN"
								}
							],
							"scoring": [
								{
									"provider_type": "imdb:votes",
									"value": 1414
								},
								{
									"provider_type": "tmdb:id",
									"value": 166017
								},
								{
									"provider_type": "imdb:multiplied",
									"value": 9332.4
								},
								{
									"provider_type": "tmdb:score",
									"value": 6.4
								},
								{
									"provider_type": "imdb:score",
									"value": 6.6
								},
								{
									"provider_type": "tmdb:popularity",
									"value": 2.75
								}
							]
						},
						{
							"jw_entity_id": "tm87681",
							"id": 87681,
							"title": "Udhaya",
							"full_path": "/in/movie/udhaya",
							"poster": "/poster/179075671/{profile}",
							"backdrops": [
								{
									"backdrop_url": "/backdrop/199849629/{profile}",
									"backdrop_blur_hash": "LNF}vCxZNGMx0f%2t6xtE2IVWqIp"
								},
								{
									"backdrop_url": "/backdrop/199849627/{profile}",
									"backdrop_blur_hash": "LMG6FnI;nNrX5+SfS$kC0~oeJTt7"
								},
								{
									"backdrop_url": "/backdrop/199849628/{profile}",
									"backdrop_blur_hash": "LMKlj:0KT{HYIna0xGtkK0ofsDNZ"
								},
								{
									"backdrop_url": "/backdrop/240463377/{profile}",
									"backdrop_blur_hash": "LGLWt#58I84;x^_4W9WA?vtQa%RP"
								},
								{
									"backdrop_url": "/backdrop/240463376/{profile}",
									"backdrop_blur_hash": "LVNTI2Wu00%2V?Imxb%LtQIB%LbG"
								}
							],
							"tmdb_popularity": 2.03,
							"object_type": "movie",
							"original_title": "உதயா",
							"offers": [
								{
									"jw_entity_id": "tm87681",
									"monetization_type": "flatrate",
									"provider_id": 119,
									"package_short_name": "prv",
									"currency": "INR",
									"urls": {
										"standard_web": "https://app.primevideo.com/detail?gti=amzn1.dv.gti.a2bdb04e-00e8-4475-86f7-d1cc0b078d42",
										"deeplink_web": "https://app.primevideo.com/watch?gti=amzn1.dv.gti.a2bdb04e-00e8-4475-86f7-d1cc0b078d42",
										"deeplink_rokuos": "launch/13?contentID=B0B2CNQXQX&MediaType=movie"
									},
									"presentation_type": "sd",
									"country": "IN"
								}
							],
							"scoring": [
								{
									"provider_type": "tmdb:score",
									"value": 5.5
								},
								{
									"provider_type": "imdb:score",
									"value": 4.3
								},
								{
									"provider_type": "tmdb:popularity",
									"value": 2.03
								},
								{
									"provider_type": "imdb:votes",
									"value": 987
								},
								{
									"provider_type": "tmdb:id",
									"value": 69658
								},
								{
									"provider_type": "imdb:multiplied",
									"value": 4244.0999999999999
								}
							]
						},
						{
							"jw_entity_id": "tm97335",
							"id": 97335,
							"title": "Karz",
							"full_path": "/in/movie/karz",
							"poster": "/poster/272159059/{profile}",
							"backdrops": [
								{
									"backdrop_url": "/backdrop/185917205/{profile}",
									"backdrop_blur_hash": "LACidQ?GIBt40L$+baI;EeInxuxa"
								}
							],
							"tmdb_popularity": 1.96,
							"object_type": "movie",
							"original_title": "कर्ज़",
							"offers": [
								{
									"jw_entity_id": "tm97335",
									"monetization_type": "flatrate",
									"provider_id": 119,
									"package_short_name": "prv",
									"currency": "INR",
									"urls": {
										"standard_web": "https://app.primevideo.com/detail?gti=amzn1.dv.gti.a5cef74f-e122-46c3-808f-178558de04d9",
										"deeplink_web": "https://app.primevideo.com/watch?gti=amzn1.dv.gti.a5cef74f-e122-46c3-808f-178558de04d9",
										"deeplink_rokuos": "launch/13?contentID=B0B1J2QL2Q&MediaType=movie"
									},
									"presentation_type": "sd",
									"country": "IN"
								}
							],
							"scoring": [
								{
									"provider_type": "tmdb:id",
									"value": 23715
								},
								{
									"provider_type": "imdb:multiplied",
									"value": 16842.4
								},
								{
									"provider_type": "tmdb:score",
									"value": 7.6
								},
								{
									"provider_type": "imdb:score",
									"value": 7.4
								},
								{
									"provider_type": "tmdb:popularity",
									"value": 1.96
								},
								{
									"provider_type": "imdb:votes",
									"value": 2276
								}
							]
						},
						{
							"jw_entity_id": "tm132024",
							"id": 132024,
							"title": "Simhadri",
							"full_path": "/in/movie/simhadri",
							"poster": "/poster/258508122/{profile}",
							"backdrops": [
								{
									"backdrop_url": "/backdrop/11501518/{profile}",
									"backdrop_blur_hash": "LMQ[O@M}?M?YDzNL-;$wY6Rkrq%2"
								},
								{
									"backdrop_url": "/backdrop/11501517/{profile}",
									"backdrop_blur_hash": "LjPi@st7_4j[.9WBV@j[WVWAoff6"
								},
								{
									"backdrop_url": "/backdrop/189732667/{profile}",
									"backdrop_blur_hash": "LRGR0HyCIo0e.7t8V@IUr=RRs-oe"
								}
							],
							"tmdb_popularity": 1.752,
							"object_type": "movie",
							"original_title": "సింహాద్రి",
							"offers": [
								{
									"jw_entity_id": "tm132024",
									"monetization_type": "flatrate",
									"provider_id": 119,
									"package_short_name": "prv",
									"currency": "INR",
									"urls": {
										"standard_web": "https://app.primevideo.com/detail?gti=amzn1.dv.gti.69b102ff-c7ad-4d6a-a649-af1ba7dce582",
										"deeplink_web": "https://app.primevideo.com/watch?gti=amzn1.dv.gti.69b102ff-c7ad-4d6a-a649-af1ba7dce582",
										"deeplink_rokuos": "launch/13?contentID=B09TQ7HPPV&MediaType=movie"
									},
									"presentation_type": "sd",
									"country": "IN"
								}
							],
							"scoring": [
								{
									"provider_type": "tmdb:score",
									"value": 6.3
								},
								{
									"provider_type": "imdb:score",
									"value": 7.4
								},
								{
									"provider_type": "tmdb:popularity",
									"value": 1.752
								},
								{
									"provider_type": "imdb:votes",
									"value": 3058
								},
								{
									"provider_type": "tmdb:id",
									"value": 80805
								},
								{
									"provider_type": "imdb:multiplied",
									"value": 22629.2
								}
							]
						},
						{
							"jw_entity_id": "tm189662",
							"id": 189662,
							"title": "Kaalamellam Kaathiruppen",
							"full_path": "/in/movie/kaalamellam-kaathiruppen",
							"poster": "/poster/141441609/{profile}",
							"tmdb_popularity": 1.375,
							"object_type": "movie",
							"original_title": "Kaalamellam Kaathiruppen",
							"offers": [
								{
									"jw_entity_id": "tm189662",
									"monetization_type": "flatrate",
									"provider_id": 119,
									"package_short_name": "prv",
									"currency": "INR",
									"urls": {
										"standard_web": "https://app.primevideo.com/detail?gti=amzn1.dv.gti.4cbac2c5-d052-4907-a523-319a21151846",
										"deeplink_web": "https://app.primevideo.com/watch?gti=amzn1.dv.gti.4cbac2c5-d052-4907-a523-319a21151846",
										"deeplink_rokuos": "launch/13?contentID=B09Y1H15VV&MediaType=movie"
									},
									"presentation_type": "sd",
									"country": "IN"
								}
							],
							"scoring": [
								{
									"provider_type": "imdb:score",
									"value": 6.9
								},
								{
									"provider_type": "tmdb:popularity",
									"value": 1.375
								},
								{
									"provider_type": "imdb:votes",
									"value": 530
								},
								{
									"provider_type": "tmdb:id",
									"value": 78650
								},
								{
									"provider_type": "imdb:multiplied",
									"value": 3657
								},
								{
									"provider_type": "tmdb:score",
									"value": 5
								}
							]
						},
						{
							"jw_entity_id": "tm21579",
							"id": 21579,
							"title": "Vaanavil",
							"full_path": "/in/movie/vaanavil",
							"poster": "/poster/278076274/{profile}",
							"backdrops": [
								{
									"backdrop_url": "/backdrop/448741/{profile}",
									"backdrop_blur_hash": "LCEoiT7%D*^4;@=rs:NH9u^4NFNG"
								}
							],
							"tmdb_popularity": 1.157,
							"object_type": "movie",
							"original_title": "வானவில்",
							"offers": [
								{
									"jw_entity_id": "tm21579",
									"monetization_type": "flatrate",
									"provider_id": 119,
									"package_short_name": "prv",
									"currency": "INR",
									"urls": {
										"standard_web": "https://app.primevideo.com/detail?gti=amzn1.dv.gti.0de5aac2-5325-4b51-86fd-22643ec3ffc6",
										"deeplink_web": "https://app.primevideo.com/watch?gti=amzn1.dv.gti.0de5aac2-5325-4b51-86fd-22643ec3ffc6",
										"deeplink_rokuos": "launch/13?contentID=B0B1W636MF&MediaType=movie"
									},
									"presentation_type": "sd",
									"country": "IN"
								}
							],
							"scoring": [
								{
									"provider_type": "imdb:score",
									"value": 6.3
								},
								{
									"provider_type": "tmdb:popularity",
									"value": 1.157
								},
								{
									"provider_type": "imdb:votes",
									"value": 12
								},
								{
									"provider_type": "tmdb:id",
									"value": 66521
								},
								{
									"provider_type": "imdb:multiplied",
									"value": 75.6
								},
								{
									"provider_type": "tmdb:score",
									"value": 5.5
								}
							]
						}
					]
				}
			]
		},
		{
			"date": "2022-05-30",
			"providers": [
				{
					"total": 6,
					"provider_id": 8,
					"items": [
						{
							"jw_entity_id": "tss306224",
							"id": 306224,
							"title": "Season 6",
							"full_path": "/in/tv-show/riverdale/season-6",
							"poster": "/poster/265046698/{profile}",
							"backdrops": [
								{
									"backdrop_url": "/backdrop/4443979/{profile}",
									"backdrop_blur_hash": "LGGaz%}=qsD%IJIVyq%0L2GGwfRi"
								},
								{
									"backdrop_url": "/backdrop/5929900/{profile}",
									"backdrop_blur_hash": "LEAl@g}8v|X9}@-BwbohD~NxkWae"
								},
								{
									"backdrop_url": "/backdrop/8632540/{profile}",
									"backdrop_blur_hash": "LJBVw-V@9bWB~VjEIVWBxvs,NGWB"
								},
								{
									"backdrop_url": "/backdrop/109898104/{profile}",
									"backdrop_blur_hash": "LbAeHsIUkDM_.TWBR-j[ozaxkWkC"
								}
							],
							"tmdb_popularity": 415.941,
							"object_type": "show_season",
							"original_title": "Season 6",
							"offers": [
								{
									"jw_entity_id": "tss306224",
									"type": "aggregated",
									"monetization_type": "flatrate",
									"provider_id": 8,
									"package_short_name": "nfx",
									"currency": "INR",
									"urls": {
										"standard_web": "http://www.netflix.com/title/80133311",
										"deeplink_web": "http://www.netflix.com/watch/80133311",
										"deeplink_rokuos": "launch/12?contentID=80133311&MediaType=show"
									},
									"presentation_type": "sd",
									"element_count": 16,
									"new_element_count": 1,
									"country": "IN"
								}
							],
							"scoring": [
								{
									"provider_type": "imdb:popularity",
									"value": 163
								},
								{
									"provider_type": "tmdb:score",
									"value": 8.5
								},
								{
									"provider_type": "imdb:score",
									"value": 6.7
								},
								{
									"provider_type": "tmdb:popularity",
									"value": 415.941
								},
								{
									"provider_type": "imdb:votes",
									"value": 139632
								},
								{
									"provider_type": "imdb:multiplied",
									"value": 935534.4
								}
							],
							"show_id": 53023,
							"show_title": "Riverdale",
							"season_number": 6
						},
						{
							"jw_entity_id": "tss350415",
							"id": 350415,
							"title": "Season 1",
							"full_path": "/in/tv-show/marriage-white-paper/season-1",
							"poster": "/poster/280849963/{profile}",
							"backdrops": [
								{
									"backdrop_url": "/backdrop/280565248/{profile}",
									"backdrop_blur_hash": "LUEE*;0yKO:ltlWXRjsmxaaKRjoz"
								},
								{
									"backdrop_url": "/backdrop/280565250/{profile}",
									"backdrop_blur_hash": "LLG9Q,9G2Twc60-;%zI;%MR%Rjbw"
								},
								{
									"backdrop_url": "/backdrop/280565249/{profile}",
									"backdrop_blur_hash": "LHEyxs56ABRi_4kUTxkXTIs.e9tR"
								}
							],
							"tmdb_popularity": 55.629,
							"object_type": "show_season",
							"original_title": "Season 1",
							"offers": [
								{
									"jw_entity_id": "tss350415",
									"type": "aggregated",
									"monetization_type": "flatrate",
									"provider_id": 8,
									"package_short_name": "nfx",
									"currency": "INR",
									"urls": {
										"standard_web": "http://www.netflix.com/title/81568851",
										"deeplink_web": "http://www.netflix.com/watch/81568851",
										"deeplink_rokuos": "launch/12?contentID=81568851&MediaType=show"
									},
									"presentation_type": "sd",
									"element_count": 4,
									"new_element_count": 1,
									"country": "IN"
								}
							],
							"scoring": [
								{
									"provider_type": "imdb:score",
									"value": 7.6
								},
								{
									"provider_type": "tmdb:popularity",
									"value": 55.629
								},
								{
									"provider_type": "imdb:votes",
									"value": 21
								},
								{
									"provider_type": "imdb:multiplied",
									"value": 159.6
								},
								{
									"provider_type": "tmdb:score",
									"value": 8.5
								}
							],
							"show_id": 344043,
							"show_title": "Welcome to Wedding Hell",
							"season_number": 1
						},
						{
							"jw_entity_id": "tm1209228",
							"id": 1209228,
							"title": "Norm Macdonald: Nothing Special",
							"full_path": "/in/movie/norm-macdonald-nothing-special",
							"poster": "/poster/281833962/{profile}",
							"backdrops": [
								{
									"backdrop_url": "/backdrop/279507797/{profile}",
									"backdrop_blur_hash": "L39QU29[4;}?4TE2Sjr:E1-pxabb"
								}
							],
							"tmdb_popularity": 50.89,
							"object_type": "movie",
							"original_title": "Norm Macdonald: Nothing Special",
							"offers": [
								{
									"jw_entity_id": "tm1209228",
									"monetization_type": "flatrate",
									"provider_id": 8,
									"package_short_name": "nfx",
									"currency": "INR",
									"urls": {
										"standard_web": "http://www.netflix.com/title/81128851",
										"deeplink_web": "http://www.netflix.com/watch/81128851",
										"deeplink_rokuos": "launch/12?contentID=81128851&MediaType=movie"
									},
									"presentation_type": "sd",
									"country": "IN"
								}
							],
							"scoring": [
								{
									"provider_type": "tmdb:id",
									"value": 975088
								},
								{
									"provider_type": "tmdb:score",
									"value": 7
								},
								{
									"provider_type": "tmdb:popularity",
									"value": 50.89
								}
							]
						},
						{
							"jw_entity_id": "tm326323",
							"id": 326323,
							"title": "The Grudge",
							"full_path": "/in/movie/the-grudge-2020",
							"poster": "/poster/163951778/{profile}",
							"backdrops": [
								{
									"backdrop_url": "/backdrop/164069492/{profile}",
									"backdrop_blur_hash": "LFCP@YWB_2t7-;WBt7t7~pj[ofj["
								},
								{
									"backdrop_url": "/backdrop/173466505/{profile}",
									"backdrop_blur_hash": "LGDb=].S0K-W?ctRIUn~.l^jIUEM"
								},
								{
									"backdrop_url": "/backdrop/160374565/{profile}",
									"backdrop_blur_hash": "LIA^BwRkE3i|~px[IVjbxu%MRQkB"
								},
								{
									"backdrop_url": "/backdrop/168289265/{profile}",
									"backdrop_blur_hash": "L94{M88w%Mf+Rjt6WBae%MMyt7oe"
								},
								{
									"backdrop_url": "/backdrop/164112217/{profile}",
									"backdrop_blur_hash": "L9BCx-*IEL^Q~Wo#D*n%HB}ta1Ef"
								}
							],
							"tmdb_popularity": 20.956,
							"object_type": "movie",
							"original_title": "The Grudge",
							"offers": [
								{
									"jw_entity_id": "tm326323",
									"monetization_type": "flatrate",
									"provider_id": 8,
									"package_short_name": "nfx",
									"currency": "INR",
									"urls": {
										"standard_web": "http://www.netflix.com/title/80219131",
										"deeplink_web": "http://www.netflix.com/watch/80219131",
										"deeplink_rokuos": "launch/12?contentID=80219131&MediaType=movie"
									},
									"available_to": "2023-05-30",
									"presentation_type": "sd",
									"country": "IN"
								}
							],
							"scoring": [
								{
									"provider_type": "imdb:multiplied",
									"value": 108269.7
								},
								{
									"provider_type": "imdb:popularity",
									"value": 2636
								},
								{
									"provider_type": "tmdb:score",
									"value": 5.6
								},
								{
									"provider_type": "imdb:score",
									"value": 4.3
								},
								{
									"provider_type": "tmdb:popularity",
									"value": 20.956
								},
								{
									"provider_type": "imdb:votes",
									"value": 25179
								},
								{
									"provider_type": "tmdb:id",
									"value": 465086
								}
							]
						},
						{
							"jw_entity_id": "tss338702",
							"id": 338702,
							"title": "Season 1",
							"full_path": "/in/tv-show/manyeo-ceryeog-nonggubu/season-1",
							"poster": "/poster/264079511/{profile}",
							"backdrops": [
								{
									"backdrop_url": "/backdrop/270813690/{profile}",
									"backdrop_blur_hash": "LZKS=AV_W3aeMqbYxafhI=WAorfl"
								}
							],
							"tmdb_popularity": 11.158,
							"object_type": "show_season",
							"original_title": "Сезон 1",
							"offers": [
								{
									"jw_entity_id": "tss338702",
									"type": "aggregated",
									"monetization_type": "flatrate",
									"provider_id": 8,
									"package_short_name": "nfx",
									"currency": "INR",
									"urls": {
										"standard_web": "http://www.netflix.com/title/81581005",
										"deeplink_web": "http://www.netflix.com/watch/81581005",
										"deeplink_rokuos": "launch/12?contentID=81581005&MediaType=show"
									},
									"presentation_type": "sd",
									"element_count": 8,
									"new_element_count": 1,
									"country": "IN"
								}
							],
							"scoring": [
								{
									"provider_type": "tmdb:popularity",
									"value": 11.158
								},
								{
									"provider_type": "tmdb:score",
									"value": 5
								}
							],
							"show_id": 329854,
							"show_title": "Jump Like a Witch",
							"season_number": 1
						},
						{
							"jw_entity_id": "tm1217611",
							"id": 1217611,
							"title": "Mighty Little Bheem: I Love Taj Mahal",
							"full_path": "/in/movie/mighty-little-bheem-i-love-taj-mahal",
							"poster": "/poster/280660386/{profile}",
							"backdrops": [
								{
									"backdrop_url": "/backdrop/280660387/{profile}",
									"backdrop_blur_hash": "LIP3*E8zD8B$%dRpM#b@-No4NL%0"
								},
								{
									"backdrop_url": "/backdrop/280660388/{profile}",
									"backdrop_blur_hash": "LnKKZ?rpGwnPKls:WIR%RkbwRPkD"
								}
							],
							"tmdb_popularity": 10.543,
							"object_type": "movie",
							"original_title": "Mighty Little Bheem: I Love Taj Mahal",
							"offers": [
								{
									"jw_entity_id": "tm1217611",
									"monetization_type": "flatrate",
									"provider_id": 8,
									"package_short_name": "nfx",
									"currency": "INR",
									"urls": {
										"standard_web": "http://www.netflix.com/title/81312752",
										"deeplink_web": "http://www.netflix.com/watch/81312752",
										"deeplink_rokuos": "launch/12?contentID=81312752&MediaType=movie"
									},
									"presentation_type": "sd",
									"country": "IN"
								}
							],
							"scoring": [
								{
									"provider_type": "tmdb:id",
									"value": 979421
								},
								{
									"provider_type": "tmdb:popularity",
									"value": 10.543
								}
							]
						}
					]
				}
			]
		},
		{
			"date": "2022-05-29",
			"providers": [
				{
					"total": 2,
					"provider_id": 8,
					"items": [
						{
							"jw_entity_id": "tss322179",
							"id": 322179,
							"title": "Season 1",
							"full_path": "/in/tv-show/our-blues/season-1",
							"poster": "/poster/270138327/{profile}",
							"backdrops": [
								{
									"backdrop_url": "/backdrop/272394963/{profile}",
									"backdrop_blur_hash": "LBDv[d4.5NQ:n9REoys:0Ksrxabd"
								},
								{
									"backdrop_url": "/backdrop/270138329/{profile}",
									"backdrop_blur_hash": "LDEo[7I9o}M_4mxvV?%3TJIA%MNZ"
								},
								{
									"backdrop_url": "/backdrop/270138328/{profile}",
									"backdrop_blur_hash": "LMMj]q9s_L-ox_s=?bWCofE1x]IV"
								},
								{
									"backdrop_url": "/backdrop/272394964/{profile}",
									"backdrop_blur_hash": "LGEpJ-RoJ4R7VtM*oet70JM{V@W?"
								},
								{
									"backdrop_url": "/backdrop/270138371/{profile}",
									"backdrop_blur_hash": "L7EyuMWB5isi4TIZRi%20K-qaNp0"
								}
							],
							"tmdb_popularity": 63.815,
							"object_type": "show_season",
							"original_title": "الموسم 1",
							"offers": [
								{
									"jw_entity_id": "tss322179",
									"type": "aggregated",
									"monetization_type": "flatrate",
									"provider_id": 8,
									"package_short_name": "nfx",
									"currency": "INR",
									"urls": {
										"standard_web": "http://www.netflix.com/title/81568842",
										"deeplink_web": "http://www.netflix.com/watch/81568842",
										"deeplink_rokuos": "launch/12?contentID=81568842&MediaType=show"
									},
									"presentation_type": "sd",
									"element_count": 16,
									"new_element_count": 1,
									"country": "IN"
								}
							],
							"scoring": [
								{
									"provider_type": "imdb:score",
									"value": 8.2
								},
								{
									"provider_type": "tmdb:popularity",
									"value": 63.815
								},
								{
									"provider_type": "imdb:votes",
									"value": 372
								},
								{
									"provider_type": "imdb:multiplied",
									"value": 3050.3999999999998
								},
								{
									"provider_type": "tmdb:score",
									"value": 8.4
								}
							],
							"show_id": 312984,
							"show_title": "Our Blues",
							"season_number": 1
						},
						{
							"jw_entity_id": "tss330460",
							"id": 330460,
							"title": "Season 1",
							"full_path": "/in/tv-show/my-liberation-diary/season-1",
							"poster": "/poster/272300956/{profile}",
							"backdrops": [
								{
									"backdrop_url": "/backdrop/272300957/{profile}",
									"backdrop_blur_hash": "LDEoVnAtH[RQ?IpH-nD*~p-:xZRj"
								},
								{
									"backdrop_url": "/backdrop/280565340/{profile}",
									"backdrop_blur_hash": "LZKJ}L9GS5X9~pIUj[xuIVt7s.oL"
								},
								{
									"backdrop_url": "/backdrop/272300958/{profile}",
									"backdrop_blur_hash": "LaHVYu9Zozs6lCfmslNFI@o#xWR%"
								},
								{
									"backdrop_url": "/backdrop/269926115/{profile}",
									"backdrop_blur_hash": "LEG*+v?a~ptR_4bJogjb~VofNGt6"
								},
								{
									"backdrop_url": "/backdrop/267832561/{profile}",
									"backdrop_blur_hash": "LWKJ}L4:NdX9~pIUj[xuD*xtsme:"
								}
							],
							"tmdb_popularity": 52.29,
							"object_type": "show_season",
							"original_title": "الموسم 1",
							"offers": [
								{
									"jw_entity_id": "tss330460",
									"type": "aggregated",
									"monetization_type": "flatrate",
									"provider_id": 8,
									"package_short_name": "nfx",
									"currency": "INR",
									"urls": {
										"standard_web": "http://www.netflix.com/title/81568411",
										"deeplink_web": "http://www.netflix.com/watch/81568411",
										"deeplink_rokuos": "launch/12?contentID=81568411&MediaType=show"
									},
									"presentation_type": "sd",
									"element_count": 16,
									"new_element_count": 1,
									"country": "IN"
								}
							],
							"scoring": [
								{
									"provider_type": "imdb:votes",
									"value": 587
								},
								{
									"provider_type": "imdb:multiplied",
									"value": 5048.2
								},
								{
									"provider_type": "tmdb:score",
									"value": 7.2
								},
								{
									"provider_type": "imdb:score",
									"value": 8.6
								},
								{
									"provider_type": "tmdb:popularity",
									"value": 52.29
								}
							],
							"show_id": 321513,
							"show_title": "My Liberation Notes",
							"season_number": 1
						}
					]
				},
				{
					"total": 1,
					"provider_id": 119,
					"items": [
						{
							"jw_entity_id": "tm1100912",
							"id": 1100912,
							"title": "Fourwalls",
							"full_path": "/in/movie/fourwalls",
							"poster": "/poster/251019426/{profile}",
							"backdrops": [
								{
									"backdrop_url": "/backdrop/280585295/{profile}",
									"backdrop_blur_hash": "LRDSj}D+MHWCEOt2K7jXD%s+x^og"
								},
								{
									"backdrop_url": "/backdrop/280585298/{profile}",
									"backdrop_blur_hash": "L78zJn0JF}rpb^NFNxxC0J?vMcxv"
								},
								{
									"backdrop_url": "/backdrop/280585297/{profile}",
									"backdrop_blur_hash": "LGE2kJu1vJ-A0{w4K6NGE1R.xvS~"
								},
								{
									"backdrop_url": "/backdrop/280585296/{profile}",
									"backdrop_blur_hash": "L7C642%f0y4VJBM{wJ%LE2IV-ox["
								},
								{
									"backdrop_url": "/backdrop/280585299/{profile}",
									"backdrop_blur_hash": "LRH-lmymVC;40xwOOYJ6I:WFxvXR"
								}
							],
							"tmdb_popularity": 1.547,
							"object_type": "movie",
							"original_title": "Fourwalls",
							"offers": [
								{
									"jw_entity_id": "tm1100912",
									"monetization_type": "flatrate",
									"provider_id": 119,
									"package_short_name": "prv",
									"currency": "INR",
									"urls": {
										"standard_web": "https://app.primevideo.com/detail?gti=amzn1.dv.gti.4dd9e476-15ae-441b-a74f-6628bbc72564",
										"deeplink_web": "https://app.primevideo.com/watch?gti=amzn1.dv.gti.4dd9e476-15ae-441b-a74f-6628bbc72564",
										"deeplink_rokuos": "launch/13?contentID=B09T99333P&MediaType=movie"
									},
									"presentation_type": "sd",
									"country": "IN"
								}
							],
							"scoring": [
								{
									"provider_type": "tmdb:id",
									"value": 970760
								},
								{
									"provider_type": "imdb:multiplied",
									"value": 940.9
								},
								{
									"provider_type": "tmdb:score",
									"value": 8
								},
								{
									"provider_type": "imdb:score",
									"value": 9.7
								},
								{
									"provider_type": "tmdb:popularity",
									"value": 1.547
								},
								{
									"provider_type": "imdb:votes",
									"value": 97
								}
							]
						}
					]
				}
			]
		},		
		{
			"date": "2022-05-23",
			"providers": [
				{
					"total": 3,
					"provider_id": 8,
					"items": [
						{
							"jw_entity_id": "tm1204317",
							"id": 1204317,
							"title": "Godspeed",
							"full_path": "/in/movie/yolun-acik-olsun",
							"poster": "/poster/273740820/{profile}",
							"backdrops": [
								{
									"backdrop_url": "/backdrop/280861770/{profile}",
									"backdrop_blur_hash": "LMGI14_2E19Gv{jXS$R:0fjYR-xt"
								},
								{
									"backdrop_url": "/backdrop/273740821/{profile}",
									"backdrop_blur_hash": "LMExws-oNHE3^i%LNIIp0gbFRlxt"
								},
								{
									"backdrop_url": "/backdrop/280377839/{profile}",
									"backdrop_blur_hash": "LlLpppV@Mxxu~pj[jEbIpJozkAju"
								},
								{
									"backdrop_url": "/backdrop/280377838/{profile}",
									"backdrop_blur_hash": "LACF*H9Fadxv0fS5W=smIn=|oeNG"
								},
								{
									"backdrop_url": "/backdrop/273740822/{profile}",
									"backdrop_blur_hash": "L7B|4m~2xlXNXa9eD,s+%DR:%3fh"
								}
							],
							"tmdb_popularity": 192.581,
							"object_type": "movie",
							"original_title": "Yolun Açik Olsun",
							"offers": [
								{
									"jw_entity_id": "tm1204317",
									"monetization_type": "flatrate",
									"provider_id": 8,
									"package_short_name": "nfx",
									"currency": "INR",
									"urls": {
										"standard_web": "http://www.netflix.com/title/81346062",
										"deeplink_web": "http://www.netflix.com/watch/81346062",
										"deeplink_rokuos": "launch/12?contentID=81346062&MediaType=movie"
									},
									"presentation_type": "sd",
									"country": "IN"
								}
							],
							"scoring": [
								{
									"provider_type": "imdb:votes",
									"value": 1044
								},
								{
									"provider_type": "tmdb:id",
									"value": 971647
								},
								{
									"provider_type": "imdb:multiplied",
									"value": 6994.8
								},
								{
									"provider_type": "tmdb:score",
									"value": 6.8
								},
								{
									"provider_type": "imdb:score",
									"value": 6.7
								},
								{
									"provider_type": "tmdb:popularity",
									"value": 192.581
								}
							]
						},
						{
							"jw_entity_id": "tss324332",
							"id": 324332,
							"title": "Season 2",
							"full_path": "/in/tv-show/ghost-in-the-shell-sac_2045/season-2",
							"poster": "/poster/277456971/{profile}",
							"backdrops": [
								{
									"backdrop_url": "/backdrop/168072246/{profile}",
									"backdrop_blur_hash": "L?Psn-oe~qRkxuofWBWBNGWBs:og"
								},
								{
									"backdrop_url": "/backdrop/191194769/{profile}",
									"backdrop_blur_hash": "LcHMmUkC0tV@Ipj[ogWBRjWWozod"
								},
								{
									"backdrop_url": "/backdrop/279005131/{profile}",
									"backdrop_blur_hash": "LF9HSIpMF#RNO[axVqVrtBV=nhaH"
								},
								{
									"backdrop_url": "/backdrop/240972155/{profile}",
									"backdrop_blur_hash": "LQ6JCEkXMcV?VBadRikCW@j=tRf,"
								},
								{
									"backdrop_url": "/backdrop/177637347/{profile}",
									"backdrop_blur_hash": "LD9jj1toPEOWTItnS#tUIToaofNt"
								}
							],
							"tmdb_popularity": 70.172,
							"object_type": "show_season",
							"original_title": "시즌 2",
							"offers": [
								{
									"jw_entity_id": "tss324332",
									"type": "aggregated",
									"monetization_type": "flatrate",
									"provider_id": 8,
									"package_short_name": "nfx",
									"currency": "INR",
									"urls": {
										"standard_web": "http://www.netflix.com/title/81030224",
										"deeplink_web": "http://www.netflix.com/watch/81030224",
										"deeplink_rokuos": "launch/12?contentID=81030224&MediaType=show"
									},
									"presentation_type": "sd",
									"element_count": 12,
									"new_element_count": 12,
									"country": "IN"
								}
							],
							"scoring": [
								{
									"provider_type": "tmdb:score",
									"value": 6.5
								},
								{
									"provider_type": "imdb:score",
									"value": 6.2
								},
								{
									"provider_type": "tmdb:popularity",
									"value": 70.172
								},
								{
									"provider_type": "imdb:votes",
									"value": 2205
								},
								{
									"provider_type": "imdb:multiplied",
									"value": 13671
								},
								{
									"provider_type": "imdb:popularity",
									"value": 4855
								}
							],
							"show_id": 103329,
							"show_title": "Ghost in the Shell: SAC_2045",
							"season_number": 2
						},
						{
							"jw_entity_id": "tm1172947",
							"id": 1172947,
							"title": "Toolsidas Junior",
							"full_path": "/in/movie/toolsidas-junior",
							"poster": "/poster/280587826/{profile}",
							"backdrops": [
								{
									"backdrop_url": "/backdrop/280411507/{profile}",
									"backdrop_blur_hash": "LO6S_oOlogjGL+i|oeWVSwr_R*oM"
								},
								{
									"backdrop_url": "/backdrop/264602125/{profile}",
									"backdrop_blur_hash": "LcHe5hIV0L%M?FoMM|M|%fNGRjt7"
								},
								{
									"backdrop_url": "/backdrop/280259259/{profile}",
									"backdrop_blur_hash": "LfJ@2Sxa0LofyCRkIUofxus:RiWB"
								},
								{
									"backdrop_url": "/backdrop/280259260/{profile}",
									"backdrop_blur_hash": "LdIE8]NH0M%LyCoyi_t7MzxtxtRk"
								}
							],
							"tmdb_popularity": 5.482,
							"object_type": "movie",
							"original_title": "तूलसीदास जूनियर",
							"offers": [
								{
									"jw_entity_id": "tm1172947",
									"monetization_type": "flatrate",
									"provider_id": 8,
									"package_short_name": "nfx",
									"currency": "INR",
									"urls": {
										"standard_web": "http://www.netflix.com/title/81107547",
										"deeplink_web": "http://www.netflix.com/watch/81107547",
										"deeplink_rokuos": "launch/12?contentID=81107547&MediaType=movie"
									},
									"presentation_type": "sd",
									"country": "IN"
								}
							],
							"scoring": [
								{
									"provider_type": "imdb:votes",
									"value": 78
								},
								{
									"provider_type": "tmdb:id",
									"value": 774806
								},
								{
									"provider_type": "imdb:multiplied",
									"value": 694.2
								},
								{
									"provider_type": "tmdb:score",
									"value": 7
								},
								{
									"provider_type": "imdb:score",
									"value": 8.9
								},
								{
									"provider_type": "tmdb:popularity",
									"value": 5.482
								}
							]
						}
					]
				},
				{
					"total": 2,
					"provider_id": 119,
					"items": [
						{
							"jw_entity_id": "tss331395",
							"id": 331395,
							"title": "Season 1",
							"full_path": "/in/tv-show/the-king-of-pigs/season-1",
							"poster": "/poster/270394050/{profile}",
							"backdrops": [
								{
									"backdrop_url": "/backdrop/270393032/{profile}",
									"backdrop_blur_hash": "LfE2wo00-;IoWBofWBofIoozj[jF"
								},
								{
									"backdrop_url": "/backdrop/270394052/{profile}",
									"backdrop_blur_hash": "LM6+@aVsIAt7H;o~x^WBVraJe-WB"
								},
								{
									"backdrop_url": "/backdrop/270394053/{profile}",
									"backdrop_blur_hash": "LHFsD1_N.lMx_LMyI;%faeNGnOxu"
								},
								{
									"backdrop_url": "/backdrop/270394055/{profile}",
									"backdrop_blur_hash": "LbJbd4DP.mY4?bIAsEkpMxRjMxaL"
								},
								{
									"backdrop_url": "/backdrop/270394054/{profile}",
									"backdrop_blur_hash": "LhHL;zDj%g%M~qoyja%MWBofRixu"
								}
							],
							"tmdb_popularity": 15.676,
							"object_type": "show_season",
							"original_title": "Stagione 1",
							"offers": [
								{
									"jw_entity_id": "tss331395",
									"type": "aggregated",
									"monetization_type": "flatrate",
									"provider_id": 119,
									"package_short_name": "prv",
									"currency": "INR",
									"urls": {
										"standard_web": "https://app.primevideo.com/detail?gti=amzn1.dv.gti.85816c1e-40de-4ef0-99a7-fc076ee5c957",
										"deeplink_web": "https://app.primevideo.com/watch?gti=amzn1.dv.gti.85816c1e-40de-4ef0-99a7-fc076ee5c957",
										"deeplink_rokuos": "launch/13?contentID=B09TJZ6RGR&MediaType=episode"
									},
									"presentation_type": "sd",
									"element_count": 6,
									"new_element_count": 2,
									"country": "IN"
								}
							],
							"scoring": [
								{
									"provider_type": "tmdb:popularity",
									"value": 15.676
								},
								{
									"provider_type": "imdb:votes",
									"value": 38
								},
								{
									"provider_type": "imdb:multiplied",
									"value": 338.2
								},
								{
									"provider_type": "tmdb:score",
									"value": 7.8
								},
								{
									"provider_type": "imdb:score",
									"value": 8.9
								}
							],
							"show_id": 321874,
							"show_title": "The King of Pigs",
							"season_number": 1
						},
						{
							"jw_entity_id": "tm823020",
							"id": 823020,
							"title": "Chola",
							"full_path": "/in/movie/shadow-of-water",
							"poster": "/poster/146194008/{profile}",
							"backdrops": [
								{
									"backdrop_url": "/backdrop/160692678/{profile}",
									"backdrop_blur_hash": "LHAu%GoL0eWVd=aytloK-payIoof"
								},
								{
									"backdrop_url": "/backdrop/160692677/{profile}",
									"backdrop_blur_hash": "LGFi3$s8~T-;t8Vs9GoM4payM|W;"
								},
								{
									"backdrop_url": "/backdrop/160692676/{profile}",
									"backdrop_blur_hash": "LHH1VLb]0NWXx?=_-nIVxYV[t6oy"
								}
							],
							"tmdb_popularity": 1.4,
							"object_type": "movie",
							"original_title": "ചോല",
							"offers": [
								{
									"jw_entity_id": "tm823020",
									"monetization_type": "flatrate",
									"provider_id": 119,
									"package_short_name": "prv",
									"currency": "INR",
									"urls": {
										"standard_web": "https://app.primevideo.com/detail?gti=amzn1.dv.gti.0ab8090b-b6d8-f9ff-f67e-f12f74c725d3",
										"deeplink_web": "https://app.primevideo.com/watch?gti=amzn1.dv.gti.0ab8090b-b6d8-f9ff-f67e-f12f74c725d3",
										"deeplink_rokuos": "launch/13?contentID=B084H33561&MediaType=movie"
									},
									"presentation_type": "sd",
									"country": "IN"
								}
							],
							"scoring": [
								{
									"provider_type": "tmdb:popularity",
									"value": 1.4
								},
								{
									"provider_type": "imdb:votes",
									"value": 389
								},
								{
									"provider_type": "tmdb:id",
									"value": 618237
								},
								{
									"provider_type": "imdb:multiplied",
									"value": 2139.5
								},
								{
									"provider_type": "tmdb:score",
									"value": 3.3
								},
								{
									"provider_type": "imdb:score",
									"value": 5.5
								}
							]
						}
					]
				}
			]
		},
		
	],
	"page": 1,
	"page_size": 10
	}
}